ruleslabs/Rules.cairo
ruleslabs/__init__.py
ruleslabs/interfaces/IRulesCards.cairo
ruleslabs/libraries/AccessControl.cairo
ruleslabs/libraries/Cards.cairo
ruleslabs/libraries/Ownable.cairo
ruleslabs/libraries/Packs.cairo
ruleslabs/libraries/Scarcity.cairo
ruleslabs/libraries/Upgradeable.cairo
ruleslabs/libraries/ERC1155/ERC1155.cairo
ruleslabs/libraries/ERC1155/ERC1155ContractURI.cairo
ruleslabs/libraries/ERC1155/IERC1155Receiver.cairo
ruleslabs/utils/card.cairo
ruleslabs/utils/constants.cairo
ruleslabs/utils/memset.cairo
ruleslabs/utils/metadata.cairo
test/upgrade.cairo
ruleslabs_core-0.20.0.dist-info/METADATA
ruleslabs_core-0.20.0.dist-info/WHEEL
ruleslabs_core-0.20.0.dist-info/top_level.txt
ruleslabs_core-0.20.0.dist-info/RECORD
